AUTHORS
CHANGELOG.txt
DESCRIPTION
LICENSE
MANIFEST.in
README.rst
setup.cfg
setup.py
django_dumpdata_field.egg-info/PKG-INFO
django_dumpdata_field.egg-info/SOURCES.txt
django_dumpdata_field.egg-info/dependency_links.txt
django_dumpdata_field.egg-info/requires.txt
django_dumpdata_field.egg-info/top_level.txt
dumpdata_field/__init__.py
dumpdata_field/models.py
dumpdata_field/management/__init__.py
dumpdata_field/management/commands/__init__.py
dumpdata_field/management/commands/dumpdata_field.py
dumpdata_field/management/commands/loaddata_field.py
dumpdata_field/tests/.coverage
dumpdata_field/tests/.coveragerc
dumpdata_field/tests/__init__.py
dumpdata_field/tests/dumpdata_field_tests.py
dumpdata_field/tests/loaddata_field_tests.py
dumpdata_field/tests/runtests.py
dumpdata_field/tests/south_settings.py
dumpdata_field/tests/test_settings.py
dumpdata_field/tests/urls.py
dumpdata_field/tests/test_app/__init__.py
dumpdata_field/tests/test_app/models.py
dumpdata_field/tests/test_app/templates/400.html
dumpdata_field/tests/test_app/templates/500.html