Metadata-Version: 1.0
Name: django-dumpdata-field
Version: 0.1
Summary: custom dumpdata and loaddata commands that allow to export given fields of a model
